querierdd.py
querierdd-0.2.3.dist-info/entry_points.txt
querierdd-0.2.3.dist-info/LICENSE
querierdd-0.2.3.dist-info/WHEEL
querierdd-0.2.3.dist-info/METADATA
querierdd-0.2.3.dist-info/RECORD
