Metadata-Version: 2.1
Name: querierdd
Version: 0.2.3
Summary: Query the system and present details in an asthetically pleasing way.
License: MIT
Author: egee-irl
Author-email: brian@egee.io
Requires-Python: >=3.6,<4.0
Classifier: License :: OSI Approved :: MIT License
Classifier: Programming Language :: Python :: 3
Classifier: Programming Language :: Python :: 3.6
Classifier: Programming Language :: Python :: 3.7
Classifier: Programming Language :: Python :: 3.8
Classifier: Programming Language :: Python :: 3.9
Requires-Dist: click (>=8.0.1,<9.0.0)
Requires-Dist: psutil (>=5.8.0,<6.0.0)
